FEV_KEGG/__init__.py
FEV_KEGG/quirks.py
FEV_KEGG/settings.py
FEV_KEGG/Drawing/Draw.py
FEV_KEGG/Drawing/Export.py
FEV_KEGG/Drawing/__init__.py
FEV_KEGG/Evolution/Clade.py
FEV_KEGG/Evolution/Comparison.py
FEV_KEGG/Evolution/Events.py
FEV_KEGG/Evolution/LUCA.py
FEV_KEGG/Evolution/Taxonomy.py
FEV_KEGG/Evolution/__init__.py
FEV_KEGG/Experiments/01.py
FEV_KEGG/Experiments/02.py
FEV_KEGG/Experiments/03.py
FEV_KEGG/Experiments/04.py
FEV_KEGG/Experiments/05.py
FEV_KEGG/Experiments/06.py
FEV_KEGG/Experiments/07.py
FEV_KEGG/Experiments/08.py
FEV_KEGG/Experiments/09.py
FEV_KEGG/Experiments/10.py
FEV_KEGG/Experiments/11.py
FEV_KEGG/Experiments/12.py
FEV_KEGG/Experiments/13.py
FEV_KEGG/Experiments/14.py
FEV_KEGG/Experiments/15.py
FEV_KEGG/Experiments/16.py
FEV_KEGG/Experiments/17.py
FEV_KEGG/Experiments/18.py
FEV_KEGG/Experiments/19.py
FEV_KEGG/Experiments/20.py
FEV_KEGG/Experiments/21.py
FEV_KEGG/Experiments/22.py
FEV_KEGG/Experiments/23.py
FEV_KEGG/Experiments/24.py
FEV_KEGG/Experiments/25.py
FEV_KEGG/Experiments/26.py
FEV_KEGG/Experiments/27.py
FEV_KEGG/Experiments/28.py
FEV_KEGG/Experiments/29.py
FEV_KEGG/Experiments/30.py
FEV_KEGG/Experiments/31.py
FEV_KEGG/Experiments/32.py
FEV_KEGG/Experiments/33.py
FEV_KEGG/Experiments/34.py
FEV_KEGG/Experiments/35.py
FEV_KEGG/Experiments/36.py
FEV_KEGG/Experiments/37.py
FEV_KEGG/Experiments/38.py
FEV_KEGG/Experiments/39.py
FEV_KEGG/Experiments/40.py
FEV_KEGG/Experiments/41.py
FEV_KEGG/Experiments/42.py
FEV_KEGG/Experiments/43.py
FEV_KEGG/Experiments/44.py
FEV_KEGG/Experiments/45.py
FEV_KEGG/Experiments/46.py
FEV_KEGG/Experiments/47.py
FEV_KEGG/Experiments/48.py
FEV_KEGG/Experiments/49.py
FEV_KEGG/Experiments/50.py
FEV_KEGG/Experiments/51.py
FEV_KEGG/Experiments/52.py
FEV_KEGG/Experiments/53.py
FEV_KEGG/Experiments/54.py
FEV_KEGG/Experiments/55.py
FEV_KEGG/Experiments/__init__.py
FEV_KEGG/Graph/Elements.py
FEV_KEGG/Graph/Models.py
FEV_KEGG/Graph/SubstanceGraphs.py
FEV_KEGG/Graph/__init__.py
FEV_KEGG/Graph/Implementations/NetworkX.py
FEV_KEGG-1.1.4.dist-info/LICENSE
FEV_KEGG-1.1.4.dist-info/METADATA
FEV_KEGG-1.1.4.dist-info/WHEEL
FEV_KEGG-1.1.4.dist-info/top_level.txt
FEV_KEGG-1.1.4.dist-info/RECORD
