Metadata-Version: 2.1
Name: FEV-KEGG
Version: 1.1.4
Summary: FEV@KEGG allows for easy analysis of metabolic networks of organisms in KEGG.
Home-page: https://github.com/ryhaberecht/FEV-KEGG
Author: Robin-Yves Haberecht
License: UNKNOWN
Project-URL: Bug Reports, https://github.com/ryhaberecht/FEV-KEGG/issues
Project-URL: Source, https://github.com/ryhaberecht/FEV-KEGG/
Keywords: bioinformatics metabolism graphs KEGG
Platform: UNKNOWN
Classifier: Development Status :: 4 - Beta
Classifier: Intended Audience :: Science/Research
Classifier: Intended Audience :: Education
Classifier: Topic :: Scientific/Engineering :: Bio-Informatics
Classifier: License :: OSI Approved :: MIT License
Classifier: Programming Language :: Python :: 3 :: Only
Classifier: Programming Language :: Python :: 3.4
Classifier: Programming Language :: Python :: 3.5
Classifier: Programming Language :: Python :: 3.6
Classifier: Environment :: Console
Requires-Python: ~=3.4
License-File: LICENSE
Requires-Dist: networkx
Requires-Dist: anytree
Requires-Dist: jsonpickle
Requires-Dist: tqdm
Requires-Dist: beautifulsoup4
Requires-Dist: retrying
Requires-Dist: appdirs
Requires-Dist: yattag
Provides-Extra: draw_image
Requires-Dist: pygraphviz ; extra == 'draw_image'
Provides-Extra: draw_window
Requires-Dist: matplotlib ; extra == 'draw_window'
Provides-Extra: python34
Requires-Dist: typing ; extra == 'python34'
